llm_proxy/__init__.py
llm_proxy/cli.py
llm_proxy/process_manager.py
llm_proxy/server.py
llm_proxy/utils.py
llm_proxy_ondemand-0.1.3.dist-info/METADATA
llm_proxy_ondemand-0.1.3.dist-info/WHEEL
llm_proxy_ondemand-0.1.3.dist-info/entry_points.txt
llm_proxy_ondemand-0.1.3.dist-info/RECORD
