Metadata-Version: 2.4
Name: llm-proxy-ondemand
Version: 0.1.3
Summary: A FastAPI proxy server for vLLM w/wo SLURM support and automatic process management
Project-URL: Homepage, https://github.com/rankun203/llm-proxy
Project-URL: Repository, https://github.com/rankun203/llm-proxy
Project-URL: Issues, https://github.com/rankun203/llm-proxy/issues
Author-email: Kun Ran <rankun203@gmail.com>
Classifier: Development Status :: 4 - Beta
Classifier: Intended Audience :: Developers
Classifier: License :: OSI Approved :: MIT License
Classifier: Programming Language :: Python :: 3
Classifier: Programming Language :: Python :: 3.10
Classifier: Programming Language :: Python :: 3.11
Classifier: Programming Language :: Python :: 3.12
Classifier: Programming Language :: Python :: 3.13
Requires-Python: >=3.10
Requires-Dist: click>=8.2.1
Requires-Dist: fastapi>=0.116.1
Requires-Dist: httpx>=0.28.1
Requires-Dist: uvicorn[standard]>=0.35.0
